LICENSE
README.md
setup.py
env_subset/main.py
env_subset.egg-info/PKG-INFO
env_subset.egg-info/SOURCES.txt
env_subset.egg-info/dependency_links.txt
env_subset.egg-info/entry_points.txt
env_subset.egg-info/top_level.txt