Metadata-Version: 2.1
Name: env-subset
Version: 1.1.0
Summary: Run a command with the subset of the current environment. env swiss army knife
Home-page: https://github.com/talwrii/env-subset
Author: @readwithai
Author-email: talwrii@gmail.com
License: BSD
Keywords: cli,environment
License-File: LICENSE
